odoo/addons/account_cutoff_accrual_sale_stock_delivery/README.rst
odoo/addons/account_cutoff_accrual_sale_stock_delivery/__init__.py
odoo/addons/account_cutoff_accrual_sale_stock_delivery/__manifest__.py
odoo/addons/account_cutoff_accrual_sale_stock_delivery/i18n/account_cutoff_accrual_sale_stock_delivery.pot
odoo/addons/account_cutoff_accrual_sale_stock_delivery/i18n/it.po
odoo/addons/account_cutoff_accrual_sale_stock_delivery/models/__init__.py
odoo/addons/account_cutoff_accrual_sale_stock_delivery/readme/CONTRIBUTORS.rst
odoo/addons/account_cutoff_accrual_sale_stock_delivery/readme/DESCRIPTION.rst
odoo/addons/account_cutoff_accrual_sale_stock_delivery/static/description/icon.png
odoo/addons/account_cutoff_accrual_sale_stock_delivery/static/description/index.html
odoo/addons/account_cutoff_accrual_sale_stock_delivery/tests/__init__.py
odoo/addons/account_cutoff_accrual_sale_stock_delivery/tests/test_cutoff_revenue_on_delivery_with_shipping.py
odoo_addon_account_cutoff_accrual_sale_stock_delivery-16.0.1.1.0.1.dist-info/METADATA
odoo_addon_account_cutoff_accrual_sale_stock_delivery-16.0.1.1.0.1.dist-info/WHEEL
odoo_addon_account_cutoff_accrual_sale_stock_delivery-16.0.1.1.0.1.dist-info/top_level.txt
odoo_addon_account_cutoff_accrual_sale_stock_delivery-16.0.1.1.0.1.dist-info/RECORD
