Metadata-Version: 2.1
Name: odoo-addon-account_cutoff_accrual_sale_stock_delivery
Version: 16.0.1.1.0.1
Summary: Glue module for Cut-Off Accruals on Sales with Stock Delivery
Home-page: https://github.com/OCA/account-closing
Author: BCIM, Odoo Community Association (OCA)
Author-email: support@odoo-community.org
License: AGPL-3
Classifier: Programming Language :: Python
Classifier: Framework :: Odoo
Classifier: Framework :: Odoo :: 16.0
Classifier: License :: OSI Approved :: GNU Affero General Public License v3
Requires-Python: >=3.10
Requires-Dist: odoo-addon-account-cutoff-accrual-sale-stock<16.1dev,>=16.0dev
Requires-Dist: odoo<16.1dev,>=16.0a
